pysamsungtv/__init__.py
pysamsungtv/client.py
pysamsungtv/connection.py
pysamsungtv/const.py
pysamsungtv/enums.py
pysamsungtv/exceptions.py
pysamsungtv/py.typed
pysamsungtv/types.py
py_samsungtv-1.0.2.dist-info/METADATA
py_samsungtv-1.0.2.dist-info/WHEEL
py_samsungtv-1.0.2.dist-info/top_level.txt
py_samsungtv-1.0.2.dist-info/RECORD
