Metadata-Version: 2.4
Name: py-samsungtv
Version: 1.0.2
Summary: Async Samsung 2024+ TV control via the HTTPS JSON-RPC interface
Author: @iloveicedgreentea
Requires-Python: >=3.11
Requires-Dist: aiohttp>=3.9
Provides-Extra: tests
Requires-Dist: pytest>=8.3; extra == "tests"
Requires-Dist: pytest-asyncio>=0.23; extra == "tests"
Requires-Dist: pytest-mypy-plugins; extra == "tests"
